siren/__init__.py
siren/commands.py
siren/models.py
siren/siren.py
siren/tests/.pytest_cache/.gitignore
siren/tests/.pytest_cache/CACHEDIR.TAG
siren/tests/.pytest_cache/README.md
siren/tests/test_commands.py
abandontech_siren-1.0.0.dist-info/LICENSE
abandontech_siren-1.0.0.dist-info/METADATA
abandontech_siren-1.0.0.dist-info/WHEEL
abandontech_siren-1.0.0.dist-info/RECORD
