Metadata-Version: 2.1
Name: abandontech-siren
Version: 1.0.0
Summary: Async Python bindings for Minecraft's RCON protocol
Home-page: https://github.com/AbandonTech/siren
License: MIT
Author: fisher60
Author-email: kyler@abandontech.com
Requires-Python: >=3.10,<4.0
Classifier: License :: OSI Approved :: MIT License
Classifier: Programming Language :: Python :: 3
Classifier: Programming Language :: Python :: 3.10
Classifier: Programming Language :: Python :: 3.11
Requires-Dist: pydantic (>=2.5.3,<3.0.0)
Project-URL: Repository, https://github.com/AbandonTech/siren
